Metadata-Version: 1.1
Name: django.js-vinta
Version: 0.8.2.dev2
Summary: Django JS Tools
Home-page: https://github.com/noirbizarre/django.js
Author: Axel Haustant
Author-email: noirbizarre+django@gmail.com
License: LGPL
Download-URL: http://pypi.python.org/pypi/django.js
Keywords: django javascript test url reverse helpers
Platform: UNKNOWN
Classifier: Framework :: Django
Classifier: Development Status :: 4 - Beta
Classifier: Programming Language :: Python
Classifier: Environment :: Web Environment
Classifier: Operating System :: OS Independent
Classifier: Intended Audience :: Developers
Classifier: Topic :: System :: Software Distribution
Classifier: Programming Language :: Python
Classifier: Programming Language :: Python :: 3
Classifier: Topic :: Software Development :: Libraries :: Python Modules
Classifier: License :: OSI Approved :: GNU Library or Lesser General Public License (LGPL)
